reho/__init__.py
reho/paths.py
reho/data/QBuildings/Geneva.ini
reho/data/QBuildings/Suisse.ini
reho/data/SIA/b_value_floor.csv
reho/data/SIA/sia2024_data.xlsx
reho/data/SIA/sia2024_rooms_sia380_1.csv
reho/data/actor/income_percentile.csv
reho/data/actor/rent_proportion.csv
reho/data/elcom/correspondance_table_municipality_operator.csv
reho/data/emissions/electricity_matrix_2019_reduced.csv
reho/data/infrastructure/AC_parameters.txt
reho/data/infrastructure/HP_parameters.txt
reho/data/infrastructure/U_values.csv
reho/data/infrastructure/building_units.csv
reho/data/infrastructure/building_units_IP.csv
reho/data/infrastructure/development.csv
reho/data/infrastructure/district_units.csv
reho/data/infrastructure/district_units_IP.csv
reho/data/infrastructure/layers.csv
reho/data/infrastructure/renovation.csv
reho/data/mobility/dailyprofiles.csv
reho/data/mobility/dailyprofiles_metadata.csv
reho/data/skydome/normalized_irradiance.csv
reho/data/skydome/skyPatchesAreas.csv
reho/data/skydome/skyPatchesCenPts.csv
reho/data/skydome/skydome.csv
reho/data/skydome/total_irradiation.csv
reho/model/__init__.py
reho/model/actors_problem.py
reho/model/infrastructure.py
reho/model/master_problem.py
reho/model/reho.py
reho/model/sub_problem.py
reho/model/ampl_model/actors_problem.mod
reho/model/ampl_model/data_stream.dat
reho/model/ampl_model/master_problem.mod
reho/model/ampl_model/scenario.mod
reho/model/ampl_model/sub_problem.mod
reho/model/ampl_model/units/air_conditioner.mod
reho/model/ampl_model/units/battery.mod
reho/model/ampl_model/units/data_heat.mod
reho/model/ampl_model/units/dhn_hex.mod
reho/model/ampl_model/units/dhn_pipes.mod
reho/model/ampl_model/units/dhwstorage.mod
reho/model/ampl_model/units/electrical_heater.mod
reho/model/ampl_model/units/electrolyzer.mod
reho/model/ampl_model/units/fuel_cell.mod
reho/model/ampl_model/units/heat_curtailment.mod
reho/model/ampl_model/units/heatpump.mod
reho/model/ampl_model/units/heatstorage.mod
reho-1.2.1.dist-info/licenses/LICENSE
reho-1.2.1.dist-info/METADATA
reho-1.2.1.dist-info/WHEEL
reho-1.2.1.dist-info/entry_points.txt
reho-1.2.1.dist-info/top_level.txt
reho-1.2.1.dist-info/RECORD
