Metadata-Version: 2.4
Name: REHO
Version: 1.2.1
Summary: Renewable Energy Hub Optimizer (REHO) - A Decision Support Tool for Renewable Energy Communities
Author-email: Dorsan Lepour <dorsan.lepour@epfl.ch>
Maintainer-email: IPESE-IT <it.ipese@epfl.ch>
License: Apache-2.0
Project-URL: Documentation, https://reho.readthedocs.io/
Project-URL: Repository, https://github.com/IPESE/REHO
Project-URL: Download, https://pypi.org/project/REHO
Keywords: MILP,MOO decision support,sustainable energy systems,energy communities
Classifier: Intended Audience :: Science/Research
Classifier: Operating System :: OS Independent
Classifier: Programming Language :: Python :: 3.9
Classifier: Programming Language :: Python :: 3.10
Classifier: Programming Language :: Python :: 3.11
Classifier: Programming Language :: Python :: 3.12
Classifier: Topic :: Scientific/Engineering
Requires-Python: <3.12,>=3.9
License-File: LICENSE
Requires-Dist: amplpy==0.15.2
Requires-Dist: ampl_module_base
Requires-Dist: ampl_module_highs
Requires-Dist: coloredlogs
Requires-Dist: geopandas<1.0.0
Requires-Dist: kaleido
Requires-Dist: matplotlib
Requires-Dist: numpy<2.0.0
Requires-Dist: openpyxl
Requires-Dist: pandas<2.0.0
Requires-Dist: plotly
Requires-Dist: psycopg2-binary<3.0.0
Requires-Dist: pvlib==0.13.0
Requires-Dist: pyclustering
Requires-Dist: pyproj
Requires-Dist: python-dotenv
Requires-Dist: pytest
Requires-Dist: qmcpy
Requires-Dist: requests
Requires-Dist: SALib
Requires-Dist: scipy
Requires-Dist: setuptools
Requires-Dist: shapely
Requires-Dist: sqlalchemy<2.0.0
Requires-Dist: sympy
Requires-Dist: urllib3<2
Dynamic: license-file
